skitso/__init__.py
skitso/atom.py
skitso/movement.py
skitso/scene.py
skitso/shapes.py
skitso-0.1.13.dist-info/LICENSE
skitso-0.1.13.dist-info/METADATA
skitso-0.1.13.dist-info/WHEEL
skitso-0.1.13.dist-info/RECORD
