Metadata-Version: 2.1
Name: skitso
Version: 0.1.13
Summary: Ligth Weigth Sketching Tool
License: MIT
Author: Javier Mansilla
Author-email: javimansilla@gmail.com
Requires-Python: >=3.10,<4.0
Classifier: License :: OSI Approved :: MIT License
Classifier: Programming Language :: Python :: 3
Classifier: Programming Language :: Python :: 3.10
Classifier: Programming Language :: Python :: 3.11
Classifier: Programming Language :: Python :: 3.12
Requires-Dist: pillow (>=10.4.0,<12.0)
